odoo/addons/ssi_inventory_closing/README.rst
odoo/addons/ssi_inventory_closing/__init__.py
odoo/addons/ssi_inventory_closing/__manifest__.py
odoo/addons/ssi_inventory_closing/menu.xml
odoo/addons/ssi_inventory_closing/data/approval_template_data.xml
odoo/addons/ssi_inventory_closing/data/ir_sequence_data.xml
odoo/addons/ssi_inventory_closing/data/policy_template_data.xml
odoo/addons/ssi_inventory_closing/data/sequence_template_data.xml
odoo/addons/ssi_inventory_closing/models/__init__.py
odoo/addons/ssi_inventory_closing/models/inventory_closing.py
odoo/addons/ssi_inventory_closing/models/inventory_closing_type.py
odoo/addons/ssi_inventory_closing/models/stock_move.py
odoo/addons/ssi_inventory_closing/models/stock_valuation_layer.py
odoo/addons/ssi_inventory_closing/security/ir.model.access.csv
odoo/addons/ssi_inventory_closing/security/ir_module_category_data.xml
odoo/addons/ssi_inventory_closing/security/ir_rule_data.xml
odoo/addons/ssi_inventory_closing/security/res_group_data.xml
odoo/addons/ssi_inventory_closing/static/description/icon.png
odoo/addons/ssi_inventory_closing/views/inventory_closing_type_views.xml
odoo/addons/ssi_inventory_closing/views/inventory_closing_views.xml
odoo14_addon_ssi_inventory_closing-14.0.1.4.0.dist-info/METADATA
odoo14_addon_ssi_inventory_closing-14.0.1.4.0.dist-info/WHEEL
odoo14_addon_ssi_inventory_closing-14.0.1.4.0.dist-info/top_level.txt
odoo14_addon_ssi_inventory_closing-14.0.1.4.0.dist-info/RECORD
